math_tools_daniel/__init__.py
math_tools_daniel/processing/__init__.py
math_tools_daniel/processing/sequences.py
math_tools_daniel/processing/statistics.py
math_tools_daniel/utils/__init__.py
math_tools_daniel/utils/math_functions.py
math_tools_daniel/utils/math_helpers.py
tests/__init__.py
tests/test_math_functions.py
tests/test_math_helpers.py
tests/test_sequences.py
tests/test_statistics.py
math_tools_daniel-1.0.1.dist-info/LICENSE
math_tools_daniel-1.0.1.dist-info/METADATA
math_tools_daniel-1.0.1.dist-info/WHEEL
math_tools_daniel-1.0.1.dist-info/top_level.txt
math_tools_daniel-1.0.1.dist-info/RECORD
