Metadata-Version: 2.1
Name: math-tools-daniel
Version: 1.0.1
Summary: Um pacote matemático completo com funções básicas e avançadas
Home-page: https://github.com/DanielSantos08/dio_suzano_python_developer/tree/master/math-tools-daniel
Author: Daniel Santos
Author-email: danfergatthi@gmail.com
License: UNKNOWN
Project-URL: Bug Reports, https://github.com/DanielSantos08/dio_suzano_python_developer/math-tools-daniel/issues
Project-URL: Source, https://github.com/DanielSantos08/dio_suzano_python_developer/math-tools-daniel
Project-URL: Documentation, https://github.com/DanielSantos08/dio_suzano_python_developer/math-tools-daniel/wiki
Keywords: mathematics,statistics,sequences,fibonacci,prime,factorial
Platform: UNKNOWN
Classifier: Development Status :: 5 - Production/Stable
Classifier: Intended Audience :: Developers
Classifier: Intended Audience :: Education
Classifier: Intended Audience :: Science/Research
Classifier: License :: OSI Approved :: MIT License
Classifier: Operating System :: OS Independent
Classifier: Programming Language :: Python :: 3
Classifier: Programming Language :: Python :: 3.8
Classifier: Programming Language :: Python :: 3.9
Classifier: Programming Language :: Python :: 3.10
Classifier: Programming Language :: Python :: 3.11
Classifier: Topic :: Scientific/Engineering :: Mathematics
Classifier: Topic :: Software Development :: Libraries :: Python Modules
Requires-Python: >=3.8
License-File: LICENSE
Provides-Extra: dev
Requires-Dist: pytest-cov (>=3.0.0) ; extra == 'dev'
Requires-Dist: pytest (>=6.0.0) ; extra == 'dev'
Provides-Extra: test
Requires-Dist: pytest-cov (>=3.0.0) ; extra == 'test'
Requires-Dist: pytest (>=6.0.0) ; extra == 'test'
